README
setup.py
axil_dates/__init__.py
axil_dates.egg-info/PKG-INFO
axil_dates.egg-info/SOURCES.txt
axil_dates.egg-info/dependency_links.txt
axil_dates.egg-info/not-zip-safe
axil_dates.egg-info/top_level.txt