Metadata-Version: 1.0
Name: axil-dates
Version: 0.1.1
Summary: axil_dates
Home-page: https://bitbucket.org/cashstar/axil_dates
Author: CashStar Inc
Author-email: kcochrane@cashstar.com
License: MIT
Keywords: django,dates,times
Platform: UNKNOWN
Classifier: Development Status :: 4 - Beta
Classifier: Environment :: Web Environment
Classifier: Operating System :: OS Independent
Classifier: Programming Language :: Python :: 2.6
Classifier: Programming Language :: Python :: 2.7
Classifier: Topic :: Software Development :: Libraries :: Python Modules
